{
  "dividends": {
    "extra_examples": [
      {
        "count": 4,
        "key": [
          "BG",
          "2026-03-26",
          "0.72"
        ]
      },
      {
        "count": 4,
        "key": [
          "WMT",
          "2024-02-20",
          "0.208"
        ]
      },
      {
        "count": 4,
        "key": [
          "WMT",
          "2026-02-19",
          "0.2475"
        ]
      },
      {
        "count": 3,
        "key": [
          "BG",
          "2025-05-15",
          "0.7"
        ]
      },
      {
        "count": 3,
        "key": [
          "GRMN",
          "2023-02-22",
          "0.73"
        ]
      },
      {
        "count": 3,
        "key": [
          "GRMN",
          "2024-02-21",
          "0.75"
        ]
      },
      {
        "count": 3,
        "key": [
          "GRMN",
          "2025-02-19",
          "0.9"
        ]
      },
      {
        "count": 3,
        "key": [
          "GRMN",
          "2026-02-18",
          "1.05"
        ]
      },
      {
        "count": 3,
        "key": [
          "ICE",
          "2024-02-08",
          "0.45"
        ]
      },
      {
        "count": 3,
        "key": [
          "ICE",
          "2025-02-06",
          "0.48"
        ]
      },
      {
        "count": 3,
        "key": [
          "ICE",
          "2026-02-05",
          "0.52"
        ]
      },
      {
        "count": 3,
        "key": [
          "LAND",
          "2023-07-11",
          "0.0462"
        ]
      },
      {
        "count": 3,
        "key": [
          "LAND",
          "2023-10-10",
          "0.0464"
        ]
      },
      {
        "count": 3,
        "key": [
          "LAND",
          "2024-01-09",
          "0.0465"
        ]
      },
      {
        "count": 3,
        "key": [
          "LAND",
          "2024-04-09",
          "0.0466"
        ]
      },
      {
        "count": 3,
        "key": [
          "LAND",
          "2024-07-09",
          "0.0467"
        ]
      },
      {
        "count": 3,
        "key": [
          "LAND",
          "2024-10-08",
          "0.0467"
        ]
      },
      {
        "count": 3,
        "key": [
          "LAND",
          "2025-01-14",
          "0.0467"
        ]
      },
      {
        "count": 3,
        "key": [
          "LAND",
          "2025-04-08",
          "0.0467"
        ]
      },
      {
        "count": 3,
        "key": [
          "LAND",
          "2025-07-10",
          "0.0467"
        ]
      },
      {
        "count": 3,
        "key": [
          "LAND",
          "2025-10-14",
          "0.0467"
        ]
      },
      {
        "count": 3,
        "key": [
          "LAND",
          "2026-01-13",
          "0.0467"
        ]
      },
      {
        "count": 3,
        "key": [
          "TEL",
          "2023-03-15",
          "0.59"
        ]
      },
      {
        "count": 3,
        "key": [
          "TEL",
          "2024-03-13",
          "0.65"
        ]
      },
      {
        "count": 3,
        "key": [
          "WMT",
          "2025-02-20",
          "0.235"
        ]
      },
      {
        "count": 2,
        "key": [
          "BG",
          "2024-02-22",
          "0.68"
        ]
      },
      {
        "count": 2,
        "key": [
          "DIS",
          "2025-11-13",
          "0.75"
        ]
      },
      {
        "count": 2,
        "key": [
          "LAND",
          "2023-04-11",
          "0.046"
        ]
      },
      {
        "count": 2,
        "key": [
          "LAND",
          "2026-04-14",
          "0.0467"
        ]
      },
      {
        "count": 2,
        "key": [
          "WMT",
          "2023-02-21",
          "0.57"
        ]
      }
    ],
    "field_exact_after_normalization": {
      "currency": 3992,
      "dividend_type": 3993,
      "ex_dividend_date": 3982,
      "frequency": 3957,
      "pay_date": 3983,
      "record_date": 3982
    },
    "graph_match_rate_percent": 90.5733,
    "graph_missing_rows": 416,
    "graph_missing_unique_keys": 415,
    "graph_rows": 4413,
    "graph_rows_on_lse_symbols": 4413,
    "graph_rows_on_missing_lse_symbols": 143,
    "graph_span": [
      "2023-01-03",
      "2026-04-27"
    ],
    "graph_total_all_symbols": 4556,
    "graph_unique_keys": 4412,
    "lse_extra_rows": 1508,
    "lse_extra_unique_keys": 1426,
    "lse_rows": 5505,
    "lse_unique_keys": 5423,
    "matched_rows": 3997,
    "matched_unique_keys": 3997,
    "missing_examples": [
      {
        "count": 2,
        "key": [
          "DVN",
          "2024-08-06",
          "0.22"
        ]
      },
      {
        "count": 1,
        "key": [
          "ABBV",
          "2024-10-30",
          "1.64"
        ]
      },
      {
        "count": 1,
        "key": [
          "ABBV",
          "2025-02-13",
          "1.64"
        ]
      },
      {
        "count": 1,
        "key": [
          "ABBV",
          "2025-06-20",
          "1.64"
        ]
      },
      {
        "count": 1,
        "key": [
          "ADM",
          "2026-02-03",
          "0.52"
        ]
      },
      {
        "count": 1,
        "key": [
          "AEIS",
          "2026-02-05",
          "0.1"
        ]
      },
      {
        "count": 1,
        "key": [
          "AES",
          "2023-02-24",
          "0.166"
        ]
      },
      {
        "count": 1,
        "key": [
          "AES",
          "2023-07-14",
          "0.166"
        ]
      },
      {
        "count": 1,
        "key": [
          "AES",
          "2023-10-06",
          "0.166"
        ]
      },
      {
        "count": 1,
        "key": [
          "AES",
          "2023-12-08",
          "0.172"
        ]
      },
      {
        "count": 1,
        "key": [
          "AES",
          "2024-02-23",
          "0.172"
        ]
      },
      {
        "count": 1,
        "key": [
          "AES",
          "2024-07-12",
          "0.172"
        ]
      },
      {
        "count": 1,
        "key": [
          "AES",
          "2024-10-11",
          "0.172"
        ]
      },
      {
        "count": 1,
        "key": [
          "ALSN",
          "2026-02-26",
          "0.29"
        ]
      },
      {
        "count": 1,
        "key": [
          "AMAT",
          "2026-03-13",
          "0.53"
        ]
      },
      {
        "count": 1,
        "key": [
          "AMT",
          "2023-05-25",
          "1.57"
        ]
      },
      {
        "count": 1,
        "key": [
          "APH",
          "2023-02-02",
          "0.21"
        ]
      },
      {
        "count": 1,
        "key": [
          "APO",
          "2024-05-02",
          "0.463"
        ]
      },
      {
        "count": 1,
        "key": [
          "APO",
          "2024-08-01",
          "0.463"
        ]
      },
      {
        "count": 1,
        "key": [
          "APO",
          "2024-11-05",
          "0.463"
        ]
      },
      {
        "count": 1,
        "key": [
          "APO",
          "2025-02-04",
          "0.463"
        ]
      },
      {
        "count": 1,
        "key": [
          "ASO",
          "2023-08-30",
          "0.09"
        ]
      },
      {
        "count": 1,
        "key": [
          "AVGO",
          "2026-03-04",
          "0.65"
        ]
      },
      {
        "count": 1,
        "key": [
          "AVY",
          "2024-07-25",
          "0.88"
        ]
      },
      {
        "count": 1,
        "key": [
          "AWK",
          "2023-04-26",
          "0.708"
        ]
      },
      {
        "count": 1,
        "key": [
          "AWK",
          "2023-07-26",
          "0.708"
        ]
      },
      {
        "count": 1,
        "key": [
          "AWK",
          "2023-10-31",
          "0.708"
        ]
      },
      {
        "count": 1,
        "key": [
          "AWK",
          "2023-12-06",
          "0.708"
        ]
      },
      {
        "count": 1,
        "key": [
          "BG",
          "2023-05-11",
          "0.662"
        ]
      },
      {
        "count": 1,
        "key": [
          "BG",
          "2023-08-17",
          "0.662"
        ]
      }
    ],
    "paired_core_rows": 3997,
    "production_node_id_comparison": {
      "conflicting_duplicate_examples": [
        {
          "id": [
            "AFL",
            "2023-11-01",
            "Regular"
          ],
          "payloads": [
            [
              "0.42",
              "USD",
              "2023-11-14",
              "Quarterly",
              "2023-12-01",
              "2023-11-15"
            ],
            [
              "0.5",
              "USD",
              "2024-02-20",
              "Quarterly",
              "2024-03-01",
              "2024-02-21"
            ]
          ]
        },
        {
          "id": [
            "AVY",
            "2024-10-25",
            "Regular"
          ],
          "payloads": [
            [
              "0.88",
              "USD",
              "2024-09-04",
              "Quarterly",
              "2024-12-18",
              "2024-09-04"
            ],
            [
              "0.88",
              "USD",
              "2024-12-04",
              "Quarterly",
              "2024-12-18",
              "2024-12-04"
            ]
          ]
        },
        {
          "id": [
            "BG",
            "2024-02-22",
            "Regular"
          ],
          "payloads": [
            [
              "0.68",
              "USD",
              "2024-05-17",
              "Quarterly",
              "2024-06-03",
              "2024-05-20"
            ],
            [
              "0.68",
              "USD",
              "2024-08-19",
              "Quarterly",
              "2024-09-02",
              "2024-08-19"
            ],
            [
              "0.68",
              "USD",
              "2025-02-18",
              "Quarterly",
              "2025-03-04",
              "2025-02-18"
            ]
          ]
        },
        {
          "id": [
            "BG",
            "2025-05-15",
            "Regular"
          ],
          "payloads": [
            [
              "0.7",
              "USD",
              "2025-05-19",
              "Quarterly",
              "2025-06-02",
              "2025-05-19"
            ],
            [
              "0.7",
              "USD",
              "2025-08-19",
              "Quarterly",
              "2025-09-02",
              "2025-08-19"
            ],
            [
              "0.7",
              "USD",
              "2025-11-17",
              "Quarterly",
              "2025-12-01",
              "2025-11-17"
            ],
            [
              "0.7",
              "USD",
              "2026-02-17",
              "Quarterly",
              "2026-03-03",
              "2026-02-17"
            ]
          ]
        },
        {
          "id": [
            "BG",
            "2026-03-26",
            "Regular"
          ],
          "payloads": [
            [
              "0.72",
              "USD",
              "2026-05-22",
              "Quarterly",
              "2026-06-01",
              "2026-05-22"
            ],
            [
              "0.72",
              "USD",
              "2026-08-18",
              "Quarterly",
              "2026-09-01",
              "2026-08-18"
            ],
            [
              "0.72",
              "USD",
              "2026-11-17",
              "Quarterly",
              "2026-12-01",
              "2026-11-17"
            ],
            [
              "0.72",
              "USD",
              "2027-02-16",
              "Quarterly",
              "2027-03-02",
              "2027-02-16"
            ]
          ]
        },
        {
          "id": [
            "CAT",
            "2023-06-14",
            "Regular"
          ],
          "payloads": [
            [
              "1.3",
              "USD",
              "2023-07-19",
              "Quarterly",
              "2023-08-18",
              "2023-07-20"
            ],
            [
              "1.3",
              "USD",
              "2023-07-20",
              null,
              "2023-08-18",
              "2023-07-21"
            ]
          ]
        },
        {
          "id": [
            "CCK",
            "2025-05-01",
            "Regular"
          ],
          "payloads": [
            [
              "0.26",
              "USD",
              "2025-03-18",
              "Quarterly",
              "2025-05-29",
              "2025-05-15"
            ],
            [
              "0.26",
              "USD",
              "2025-05-15",
              "Quarterly",
              "2025-05-29",
              "2025-05-15"
            ]
          ]
        },
        {
          "id": [
            "DIS",
            "2024-12-04",
            "Regular"
          ],
          "payloads": [
            [
              "0.5",
              "USD",
              "2024-12-16",
              "BiAnnual",
              "2025-01-16",
              "2024-12-16"
            ],
            [
              "0.5",
              "USD",
              "2025-06-24",
              "BiAnnual",
              "2025-07-23",
              "2025-06-24"
            ]
          ]
        },
        {
          "id": [
            "DIS",
            "2025-11-13",
            "Regular"
          ],
          "payloads": [
            [
              "0.75",
              "USD",
              "2025-12-15",
              "BiAnnual",
              "2026-01-15",
              "2025-12-15"
            ],
            [
              "0.75",
              "USD",
              "2026-06-30",
              "BiAnnual",
              "2026-07-22",
              "2026-06-30"
            ]
          ]
        },
        {
          "id": [
            "EOG",
            "2023-02-23",
            "Regular"
          ],
          "payloads": [
            [
              "0.825",
              "USD",
              "2023-04-13",
              "Quarterly",
              "2023-04-28",
              "2023-04-14"
            ],
            [
              "1",
              "USD",
              "2023-03-15",
              "OneTime",
              "2023-03-30",
              "2023-03-16"
            ]
          ]
        },
        {
          "id": [
            "EOG",
            "2023-11-02",
            "Regular"
          ],
          "payloads": [
            [
              "0.91",
              "USD",
              "2024-01-16",
              "Quarterly",
              "2024-01-31",
              "2024-01-17"
            ],
            [
              "1.5",
              "USD",
              "2023-12-14",
              "OneTime",
              "2023-12-29",
              "2023-12-15"
            ]
          ]
        },
        {
          "id": [
            "GRMN",
            "2023-02-22",
            "Regular"
          ],
          "payloads": [
            [
              "0.73",
              "USD",
              "2023-06-16",
              "Quarterly",
              "2023-06-30",
              "2023-06-20"
            ],
            [
              "0.73",
              "USD",
              "2023-09-14",
              "Quarterly",
              "2023-09-29",
              "2023-09-15"
            ],
            [
              "0.73",
              "USD",
              "2023-12-14",
              "Quarterly",
              "2023-12-29",
              "2023-12-15"
            ],
            [
              "0.73",
              "USD",
              "2024-03-14",
              "Quarterly",
              "2024-03-29",
              "2024-03-15"
            ]
          ]
        },
        {
          "id": [
            "GRMN",
            "2024-02-21",
            "Regular"
          ],
          "payloads": [
            [
              "0.75",
              "USD",
              "2024-06-17",
              "Quarterly",
              "2024-06-28",
              "2024-06-17"
            ],
            [
              "0.75",
              "USD",
              "2024-09-13",
              "Quarterly",
              "2024-12-27",
              "2024-09-13"
            ],
            [
              "0.75",
              "USD",
              "2024-12-13",
              "Quarterly",
              "2024-12-27",
              "2024-12-13"
            ],
            [
              "0.75",
              "USD",
              "2025-03-14",
              "Quarterly",
              "2025-03-28",
              "2025-03-14"
            ]
          ]
        },
        {
          "id": [
            "GRMN",
            "2025-02-19",
            "Regular"
          ],
          "payloads": [
            [
              "0.9",
              "USD",
              "2025-06-16",
              "Quarterly",
              "2025-06-27",
              "2025-06-16"
            ],
            [
              "0.9",
              "USD",
              "2025-09-12",
              "Quarterly",
              "2025-09-26",
              "2025-09-12"
            ],
            [
              "0.9",
              "USD",
              "2025-12-12",
              "Quarterly",
              "2025-12-26",
              "2025-12-12"
            ],
            [
              "0.9",
              "USD",
              "2026-03-13",
              "Quarterly",
              "2026-03-27",
              "2026-03-13"
            ]
          ]
        },
        {
          "id": [
            "GRMN",
            "2026-02-18",
            "Regular"
          ],
          "payloads": [
            [
              "1.05",
              "USD",
              "2026-06-15",
              "Quarterly",
              "2026-06-26",
              "2026-06-15"
            ],
            [
              "1.05",
              "USD",
              "2026-09-11",
              "Quarterly",
              "2026-09-25",
              "2026-09-11"
            ],
            [
              "1.05",
              "USD",
              "2026-12-11",
              "Quarterly",
              "2026-12-24",
              "2026-12-11"
            ],
            [
              "1.05",
              "USD",
              "2027-03-12",
              "Quarterly",
              "2027-03-26",
              "2027-03-12"
            ]
          ]
        },
        {
          "id": [
            "ICE",
            "2024-02-08",
            "Regular"
          ],
          "payloads": [
            [
              "0.45",
              "USD",
              "2024-03-14",
              "Quarterly",
              "2024-03-29",
              "2024-03-15"
            ],
            [
              "0.45",
              "USD",
              "2024-06-13",
              "Quarterly",
              "2024-06-28",
              "2024-06-13"
            ],
            [
              "0.45",
              "USD",
              "2024-09-16",
              "Quarterly",
              "2024-09-30",
              "2024-09-16"
            ],
            [
              "0.45",
              "USD",
              "2024-12-16",
              "Quarterly",
              "2024-12-31",
              "2024-12-16"
            ]
          ]
        },
        {
          "id": [
            "ICE",
            "2025-02-06",
            "Regular"
          ],
          "payloads": [
            [
              "0.48",
              "USD",
              "2025-03-17",
              "Quarterly",
              "2025-03-31",
              "2025-03-17"
            ],
            [
              "0.48",
              "USD",
              "2025-06-13",
              "Quarterly",
              "2025-06-30",
              "2025-06-13"
            ],
            [
              "0.48",
              "USD",
              "2025-09-16",
              "Quarterly",
              "2025-09-30",
              "2025-09-16"
            ],
            [
              "0.48",
              "USD",
              "2025-12-16",
              "Quarterly",
              "2025-12-31",
              "2025-12-16"
            ]
          ]
        },
        {
          "id": [
            "ICE",
            "2026-02-05",
            "Regular"
          ],
          "payloads": [
            [
              "0.52",
              "USD",
              "2026-03-17",
              "Quarterly",
              "2026-03-31",
              "2026-03-17"
            ],
            [
              "0.52",
              "USD",
              "2026-06-15",
              "Quarterly",
              "2026-06-30",
              "2026-06-15"
            ],
            [
              "0.52",
              "USD",
              "2026-09-16",
              "Quarterly",
              "2026-09-30",
              "2026-09-16"
            ],
            [
              "0.52",
              "USD",
              "2026-12-16",
              "Quarterly",
              "2026-12-31",
              "2026-12-16"
            ]
          ]
        },
        {
          "id": [
            "LAND",
            "2023-01-10",
            "Regular"
          ],
          "payloads": [
            [
              "0.0459",
              "USD",
              "2023-03-16",
              "Monthly",
              "2023-03-31",
              "2023-03-17"
            ],
            [
              "0.046",
              "USD",
              "2023-01-19",
              "Monthly",
              "2023-01-31",
              "2023-01-20"
            ],
            [
              "0.046",
              "USD",
              "2023-02-16",
              "Monthly",
              "2023-02-28",
              "2023-02-17"
            ]
          ]
        },
        {
          "id": [
            "LAND",
            "2023-04-11",
            "Regular"
          ],
          "payloads": [
            [
              "0.046",
              "USD",
              "2023-04-20",
              "Monthly",
              "2023-04-28",
              "2023-04-21"
            ],
            [
              "0.046",
              "USD",
              "2023-05-22",
              "Monthly",
              "2023-05-31",
              "2023-05-23"
            ],
            [
              "0.046",
              "USD",
              "2023-06-20",
              "Monthly",
              "2023-06-30",
              "2023-06-21"
            ]
          ]
        }
      ],
      "field_any_exact_after_normalization": {
        "cash_amount": 3993,
        "currency": 4328,
        "ex_dividend_date": 4332,
        "frequency": 4278,
        "pay_date": 4329,
        "record_date": 4331
      },
      "graph_missing_ids": 80,
      "graph_unique_ids": 4413,
      "ids_with_any_exact_cash_amount": 3993,
      "ids_with_any_exact_full_payload": 3940,
      "lse_conflicting_duplicate_ids": 45,
      "lse_duplicate_ids": 45,
      "lse_duplicate_rows_beyond_one_per_id": 89,
      "lse_extra_ids": 1083,
      "lse_unique_ids": 5416,
      "missing_id_examples": [
        [
          "ADM",
          "2026-02-03",
          "Regular"
        ],
        [
          "AEIS",
          "2026-02-05",
          "Regular"
        ],
        [
          "ALSN",
          "2026-02-26",
          "Regular"
        ],
        [
          "AMAT",
          "2026-03-13",
          "Regular"
        ],
        [
          "APH",
          "2023-02-02",
          "Regular"
        ],
        [
          "ASO",
          "2023-08-30",
          "Regular"
        ],
        [
          "AVGO",
          "2026-03-04",
          "Regular"
        ],
        [
          "AVY",
          "2024-07-25",
          "Regular"
        ],
        [
          "BRX",
          "2026-02-09",
          "Regular"
        ],
        [
          "BRX",
          "2026-04-27",
          "Regular"
        ],
        [
          "CAG",
          "2026-03-31",
          "Regular"
        ],
        [
          "CASY",
          "2026-03-09",
          "Regular"
        ],
        [
          "CBRL",
          "2026-03-04",
          "Regular"
        ],
        [
          "CCK",
          "2025-02-27",
          "Regular"
        ],
        [
          "CEG",
          "2026-02-24",
          "Regular"
        ],
        [
          "CG",
          "2025-08-07",
          "Regular"
        ],
        [
          "CMCSA",
          "2026-01-29",
          "Regular"
        ],
        [
          "COST",
          "2023-12-13",
          "Special"
        ],
        [
          "CRM",
          "2026-02-25",
          "Regular"
        ],
        [
          "DELL",
          "2026-03-02",
          "Regular"
        ],
        [
          "DIS",
          "2023-11-30",
          "Special"
        ],
        [
          "DRI",
          "2026-03-19",
          "Regular"
        ],
        [
          "DVN",
          "2023-02-14",
          "Regular"
        ],
        [
          "DVN",
          "2024-05-01",
          "Regular"
        ],
        [
          "DVN",
          "2024-08-06",
          "Special"
        ],
        [
          "EOG",
          "2023-02-23",
          "Special"
        ],
        [
          "EOG",
          "2023-11-02",
          "Special"
        ],
        [
          "F",
          "2024-02-06",
          "Special"
        ],
        [
          "F",
          "2025-02-06",
          "Special"
        ],
        [
          "FANG",
          "2023-02-21",
          "Regular"
        ]
      ],
      "overlap_ids": 4333,
      "rule": "Production Dividend node ID is ticker + declaration_date + normalized dividend_type; cash amount is a property, not part of the ID."
    },
    "symbols_requested": 418
  },
  "errors": {},
  "generated_at_utc": "2026-07-19T16:15:30+00:00",
  "method": {
    "comparison_scope": "Graph records whose ticker exists in the LSE stock catalog; LSE rows locally restricted to the graph date span.",
    "dividend_core": [
      "ticker/symbol",
      "declaration_date",
      "cash_amount/dividend_amount"
    ],
    "split_core": [
      "ticker/symbol",
      "execution_date/effective_date",
      "split_from",
      "split_to"
    ]
  },
  "safety": "Neo4j READ_ACCESS/execute_read and LSE GET requests only. No key was printed or saved; no production data was changed.",
  "splits": {
    "extra_examples": [],
    "graph_match_rate_percent": 100.0,
    "graph_missing_rows": 0,
    "graph_missing_unique_keys": 0,
    "graph_rows": 38,
    "graph_rows_on_lse_symbols": 38,
    "graph_rows_on_missing_lse_symbols": 2,
    "graph_span": [
      "2023-01-04",
      "2026-02-09"
    ],
    "graph_total_all_symbols": 40,
    "graph_unique_keys": 38,
    "lse_extra_rows": 0,
    "lse_extra_unique_keys": 0,
    "lse_rows": 38,
    "lse_unique_keys": 38,
    "matched_rows": 38,
    "matched_unique_keys": 38,
    "missing_examples": [],
    "symbols_requested": 36
  },
  "truncated_symbol_endpoints": []
}
