{
  "bucket": "denylist_adjacent",
  "packet_count": 20,
  "verdicts": [
    {
      "accession_8k": "0000874761-23-000004",
      "ticker": "AES",
      "claimed_fy": 2022,
      "claimed_q": "Q4",
      "verdict": "ok",
      "evidence": "reported financial results for the year ended December 31, 2022",
      "evidence_url": "https://www.sec.gov/Archives/edgar/data/874761/000087476123000004/q42022earningsreleaseexs.htm",
      "no_ex_99_1": true,
      "no_ex_99_1_resolution": "EX-99 (q42022earningsreleaseexs.htm) found in archive; explicitly reports full year ended Dec 31, 2022 (Q4/annual)",
      "reasoning": "Q4 2022 earnings release (annual+Q4); period and fiscal year match xbrl claim FY2022 Q4"
    },
    {
      "accession_8k": "0000874761-25-000006",
      "ticker": "AES",
      "claimed_fy": 2024,
      "claimed_q": "Q4",
      "verdict": "ok",
      "evidence": "AES Achieves 2024 Strategic & Financial Goals",
      "evidence_url": "https://www.sec.gov/Archives/edgar/data/874761/000087476125000006/",
      "no_ex_99_1": false,
      "no_ex_99_1_resolution": null,
      "reasoning": "Press release headline reports 2024 full-year (Q4/annual) results; matches xbrl FY2024 Q4"
    },
    {
      "accession_8k": "0001104659-23-086819",
      "ticker": "CAKE",
      "claimed_fy": 2023,
      "claimed_q": "Q2",
      "verdict": "ok",
      "evidence": "REPORTS RESULTS FOR SECOND QUARTER OF FISCAL 2023",
      "evidence_url": "https://www.sec.gov/Archives/edgar/data/887596/000110465923086819/",
      "no_ex_99_1": false,
      "no_ex_99_1_resolution": null,
      "reasoning": "Press release explicitly states Q2 fiscal 2023; matches xbrl FY2023 Q2"
    },
    {
      "accession_8k": "0001104659-24-058691",
      "ticker": "CAKE",
      "claimed_fy": 2024,
      "claimed_q": "Q1",
      "verdict": "ok",
      "evidence": "REPORTS RESULTS FOR FIRST QUARTER OF FISCAL 2024",
      "evidence_url": "https://www.sec.gov/Archives/edgar/data/887596/000110465924058691/",
      "no_ex_99_1": false,
      "no_ex_99_1_resolution": null,
      "reasoning": "Press release explicitly states Q1 fiscal 2024; matches xbrl FY2024 Q1"
    },
    {
      "accession_8k": "0001104659-24-084383",
      "ticker": "CAKE",
      "claimed_fy": 2024,
      "claimed_q": "Q2",
      "verdict": "ok",
      "evidence": "REPORTS RESULTS FOR SECOND QUARTER OF FISCAL 2024",
      "evidence_url": "https://www.sec.gov/Archives/edgar/data/887596/000110465924084383/",
      "no_ex_99_1": false,
      "no_ex_99_1_resolution": null,
      "reasoning": "Press release explicitly states Q2 fiscal 2024; matches xbrl FY2024 Q2"
    },
    {
      "accession_8k": "0001104659-24-112254",
      "ticker": "CAKE",
      "claimed_fy": 2024,
      "claimed_q": "Q3",
      "verdict": "ok",
      "evidence": "REPORTS RESULTS FOR THIRD QUARTER OF FISCAL 2024",
      "evidence_url": "https://www.sec.gov/Archives/edgar/data/887596/000110465924112254/",
      "no_ex_99_1": false,
      "no_ex_99_1_resolution": null,
      "reasoning": "Press release explicitly states Q3 fiscal 2024; matches xbrl FY2024 Q3"
    },
    {
      "accession_8k": "0001104659-25-015185",
      "ticker": "CAKE",
      "claimed_fy": 2024,
      "claimed_q": "Q4",
      "verdict": "ok",
      "evidence": "REPORTS RESULTS FOR FOURTH QUARTER OF FISCAL 2024",
      "evidence_url": "https://www.sec.gov/Archives/edgar/data/887596/000110465925015185/",
      "no_ex_99_1": false,
      "no_ex_99_1_resolution": null,
      "reasoning": "Press release explicitly states Q4 fiscal 2024; matches xbrl FY2024 Q4"
    },
    {
      "accession_8k": "0001104659-25-042573",
      "ticker": "CAKE",
      "claimed_fy": 2025,
      "claimed_q": "Q1",
      "verdict": "ok",
      "evidence": "REPORTS RESULTS FOR FIRST QUARTER OF FISCAL 2025",
      "evidence_url": "https://www.sec.gov/Archives/edgar/data/887596/000110465925042573/",
      "no_ex_99_1": false,
      "no_ex_99_1_resolution": null,
      "reasoning": "Press release explicitly states Q1 fiscal 2025; matches xbrl FY2025 Q1"
    },
    {
      "accession_8k": "0001104659-25-071758",
      "ticker": "CAKE",
      "claimed_fy": 2025,
      "claimed_q": "Q2",
      "verdict": "ok",
      "evidence": "REPORTS RESULTS FOR SECOND QUARTER OF FISCAL 2025",
      "evidence_url": "https://www.sec.gov/Archives/edgar/data/887596/000110465925071758/",
      "no_ex_99_1": false,
      "no_ex_99_1_resolution": null,
      "reasoning": "Press release explicitly states Q2 fiscal 2025; matches xbrl FY2025 Q2"
    },
    {
      "accession_8k": "0001104659-26-017090",
      "ticker": "CAKE",
      "claimed_fy": 2025,
      "claimed_q": "Q4",
      "verdict": "ok",
      "evidence": "REPORTS RESULTS FOR FOURTH QUARTER OF FISCAL 2025",
      "evidence_url": "https://www.sec.gov/Archives/edgar/data/887596/000110465926017090/",
      "no_ex_99_1": false,
      "no_ex_99_1_resolution": null,
      "reasoning": "Press release explicitly states Q4 fiscal 2025; matches xbrl FY2025 Q4"
    },
    {
      "accession_8k": "0001104659-24-012551",
      "ticker": "PLCE",
      "claimed_fy": 2024,
      "claimed_q": "Q4",
      "verdict": "ok",
      "evidence": "preliminary unaudited results for the fourth quarter of fiscal 2023",
      "evidence_url": "https://www.sec.gov/Archives/edgar/data/1041859/000110465924012551/",
      "no_ex_99_1": false,
      "no_ex_99_1_resolution": null,
      "reasoning": "Non-Dec FYE: company's own 'fiscal 2023' (period ending Feb 3, 2024) = XBRL fy=2024; matches Q4 claim per fiscal-year semantics rule"
    },
    {
      "accession_8k": "0001558370-23-000847",
      "ticker": "RH",
      "claimed_fy": 2023,
      "claimed_q": "Q4",
      "verdict": "unclear",
      "evidence": "updating our fiscal 2022 outlook by confirming that we now expect fiscal 2022 revenue",
      "evidence_url": "https://www.sec.gov/Archives/edgar/data/1528849/000155837023000847/rh-20230201x8k.htm",
      "no_ex_99_1": true,
      "no_ex_99_1_resolution": "No EX-99.1 in archive; 8-K body is a restatement notice (Item 4.02) with fiscal 2022 outlook update, not a quarter-stating earnings release. No explicit Q4 statement.",
      "reasoning": "Filing is a restatement/non-reliance notice for prior fiscal 2022 quarters; does not explicitly report a specific quarter's results"
    },
    {
      "accession_8k": "0001558370-23-004922",
      "ticker": "RH",
      "claimed_fy": 2023,
      "claimed_q": "Q4",
      "verdict": "ok",
      "evidence": "RH REPORTS FOURTH QUARTER AND FISCAL YEAR 2022 RESULTS",
      "evidence_url": "https://www.sec.gov/Archives/edgar/data/1528849/000155837023004922/",
      "no_ex_99_1": false,
      "no_ex_99_1_resolution": null,
      "reasoning": "Non-Dec FYE: RH's own 'fiscal year 2022' ended Jan 28, 2023 = XBRL fy=2023; matches Q4 claim per fiscal-year semantics rule"
    },
    {
      "accession_8k": "0001558370-24-004085",
      "ticker": "RH",
      "claimed_fy": 2024,
      "claimed_q": "Q4",
      "verdict": "ok",
      "evidence": "RH REPORTS FOURTH QUARTER AND FISCAL YEAR 2023 RESULTS",
      "evidence_url": "https://www.sec.gov/Archives/edgar/data/1528849/000155837024004085/",
      "no_ex_99_1": false,
      "no_ex_99_1_resolution": null,
      "reasoning": "Non-Dec FYE: RH's own 'fiscal year 2023' ended Feb 3, 2024 = XBRL fy=2024; matches Q4 claim per fiscal-year semantics rule"
    },
    {
      "accession_8k": "0001604028-23-000006",
      "ticker": "WMS",
      "claimed_fy": 2023,
      "claimed_q": "Q3",
      "verdict": "ok",
      "evidence": "ANNOUNCES THIRD QUARTER FISCAL 2023 RESULTS",
      "evidence_url": "https://www.sec.gov/Archives/edgar/data/1604028/000160402823000006/",
      "no_ex_99_1": false,
      "no_ex_99_1_resolution": null,
      "reasoning": "Press release explicitly states Q3 fiscal 2023; matches xbrl FY2023 Q3"
    },
    {
      "accession_8k": "0001604028-23-000012",
      "ticker": "WMS",
      "claimed_fy": 2023,
      "claimed_q": "Q4",
      "verdict": "ok",
      "evidence": "ANNOUNCES FOURTH QUARTER AND FISCAL YEAR 2023 RESULTS",
      "evidence_url": "https://www.sec.gov/Archives/edgar/data/1604028/000160402823000012/",
      "no_ex_99_1": false,
      "no_ex_99_1_resolution": null,
      "reasoning": "Press release explicitly states Q4/fiscal year 2023; matches xbrl FY2023 Q4"
    },
    {
      "accession_8k": "0001604028-24-000008",
      "ticker": "WMS",
      "claimed_fy": 2024,
      "claimed_q": "Q4",
      "verdict": "ok",
      "evidence": "ANNOUNCES FOURTH QUARTER AND FISCAL YEAR 2024 RESULTS",
      "evidence_url": "https://www.sec.gov/Archives/edgar/data/1604028/000160402824000008/",
      "no_ex_99_1": false,
      "no_ex_99_1_resolution": null,
      "reasoning": "Press release explicitly states Q4/fiscal year 2024; matches xbrl FY2024 Q4"
    },
    {
      "accession_8k": "0001604028-24-000041",
      "ticker": "WMS",
      "claimed_fy": 2025,
      "claimed_q": "Q2",
      "verdict": "ok",
      "evidence": "ANNOUNCES SECOND QUARTER FISCAL 2025 RESULTS",
      "evidence_url": "https://www.sec.gov/Archives/edgar/data/1604028/000160402824000041/",
      "no_ex_99_1": false,
      "no_ex_99_1_resolution": null,
      "reasoning": "Press release explicitly states Q2 fiscal 2025; matches xbrl FY2025 Q2"
    },
    {
      "accession_8k": "0001604028-25-000002",
      "ticker": "WMS",
      "claimed_fy": 2025,
      "claimed_q": "Q3",
      "verdict": "ok",
      "evidence": "ANNOUNCES THIRD QUARTER FISCAL 2025 RESULTS",
      "evidence_url": "https://www.sec.gov/Archives/edgar/data/1604028/000160402825000002/",
      "no_ex_99_1": false,
      "no_ex_99_1_resolution": null,
      "reasoning": "Press release explicitly states Q3 fiscal 2025; matches xbrl FY2025 Q3"
    },
    {
      "accession_8k": "0001604028-25-000009",
      "ticker": "WMS",
      "claimed_fy": 2025,
      "claimed_q": "Q4",
      "verdict": "ok",
      "evidence": "ANNOUNCES FOURTH QUARTER AND FISCAL YEAR 2025 RESULTS",
      "evidence_url": "https://www.sec.gov/Archives/edgar/data/1604028/000160402825000009/",
      "no_ex_99_1": false,
      "no_ex_99_1_resolution": null,
      "reasoning": "Press release explicitly states Q4/fiscal year 2025; matches xbrl FY2025 Q4"
    }
  ],
  "summary": {"ok": 19, "wrong": 0, "unclear": 1}
}
